betaMixPy/__init__.py
betaMixPy/betaMixPy.py
betaMixPy-0.1.4.dist-info/LICENSE
betaMixPy-0.1.4.dist-info/METADATA
betaMixPy-0.1.4.dist-info/WHEEL
betaMixPy-0.1.4.dist-info/top_level.txt
betaMixPy-0.1.4.dist-info/RECORD
