Metadata-Version: 2.1
Name: betaMixPy
Version: 0.1.4
Summary: A Python package to find strong correlations among P variables, each with N observations.
Home-page: https://pypi.org/project/betaMixPy/
Author: Haim Bar
Author-email: haim.bar@uconn.edu
Classifier: Programming Language :: Python :: 3
Classifier: License :: OSI Approved :: MIT License
Classifier: Operating System :: OS Independent
License-File: LICENSE
Requires-Dist: statistics
Requires-Dist: matplotlib
Requires-Dist: pandas
Requires-Dist: networkx
Requires-Dist: numpy
Requires-Dist: scipy
